illallangi/http/__init__.py
illallangi/http/__version__.py
illallangi/http/tools.py
illallangi_http-0.1.0.dist-info/METADATA
illallangi_http-0.1.0.dist-info/WHEEL
illallangi_http-0.1.0.dist-info/entry_points.txt
illallangi_http-0.1.0.dist-info/licenses/LICENSE
illallangi_http-0.1.0.dist-info/RECORD
